MUX21_different/mux_21_diff.vhdl
library IEEE;
use IEEE.std_logic_1164.all;

ENTITY mux_21_diff IS PORT
(
	d: IN std_logic_vector(1 downto 0);
	a: IN std_logic;
	e: IN std_logic;
	y: OUT std_logic);
END mux_21_diff;

ARCHITECTURE arch OF mux_21_diff IS
BEGIN
	PROCESS(d,a,e)
	BEGIN
		if e = '0' then
			y <= '0';
		elsif a = '0' then
			y <= d(0);
		elsif a = '1' then
			y <= d(1);
		else 
			y <= '0';
		end if;
	END PROCESS;
END arch;

MUX21_different/tb.vhdl
library IEEE;
use IEEE.std_logic_1164.all;

ENTITY tb IS 
END tb;

ARCHITECTURE arch OF tb IS
	COMPONENT mux_21_diff
	PORT
	(
		d: IN std_logic_vector(1 DOWNTO 0);
		a: IN std_logic;
		e: IN std_logic;
		y: OUT std_logic);
	END COMPONENT;

	SIGNAL a,e,y : std_logic;
	SIGNAL d : std_logic_vector(1 downto 0);
BEGIN
	mux : mux_21_diff port map(d => d, a => a, e => e, y => y);

	PROCESS BEGIN
		d <= "XX";
		a <= 'X';
		e <= 'X';
		wait for 1 ns;
		
		d <= "00";
		a <= '0';
		e <= '0';
		wait for 1 ns;
		
		d <= "00";
		a <= '0';
		e <= '0';
		wait for 1 ns;
		
		d <= "00";
		a <= '0';
		e <= '1';
		wait for 1 ns;
		
		d <= "00";
		a <= '1';
		e <= '0';
		wait for 1 ns;
		
		d <= "00";
		a <= '1';
		e <= '1';
		wait for 1 ns;
		
		d <= "01";
		a <= '0';
		e <= '0';
		wait for 1 ns;
		
		d <= "01";
		a <= '0';
		e <= '1';
		wait for 1 ns;
		
		d <= "01";
		a <= '1';
		e <= '0';
		wait for 1 ns;
		
		d <= "01";
		a <= '1';
		e <= '1';
		wait for 1 ns;
		
		d <= "10";
		a <= '0';
		e <= '0';
		wait for 1 ns;
		
		d <= "10";
		a <= '0';
		e <= '1';
		wait for 1 ns;
		
		d <= "10";
		a <= '1';
		e <= '0';
		wait for 1 ns;

		d <= "10";
		a <= '1';
		e <= '1';
		wait for 1 ns;
		
		assert false report "End of test";
		WAIT;
	END PROCESS;
END arch;

MUX21_different/waveform.vcd
$date
  Mon Apr 15 14:01:50 2019
$end
$version
  GHDL v0
$end
$timescale
  1 fs
$end
$scope module standard $end
$upscope $end
$scope module std_logic_1164 $end
$upscope $end
$scope module tb $end
$var reg 1 ! a $end
$var reg 1 " e $end
$var reg 1 # y $end
$var reg 2 $ d[1:0] $end
$scope module mux $end
$var reg 2 % d[1:0] $end
$var reg 1 & a $end
$var reg 1 ' e $end
$var reg 1 ( y $end
$upscope $end
$upscope $end
$enddefinitions $end
#0
X!
X"
0#
bXX $
bXX %
X&
X'
0(
#1000000
0!
0"
b00 $
b00 %
0&
0'
#2000000
#3000000
1"
1'
#4000000
1!
0"
1&
0'
#5000000
1"
1'
#6000000
0!
0"
b01 $
b01 %
0&
0'
#7000000
1"
1#
1'
1(
#8000000
1!
0"
0#
1&
0'
0(
#9000000
1"
1'
#10000000
0!
0"
b10 $
b10 %
0&
0'
#11000000
1"
1'
#12000000
1!
0"
1&
0'
#13000000
1"
1#
1'
1(
