Structural_AND_OR_AND/sklopAND.vhdl
library IEEE;
use IEEE.std_logic_1164.all;

ENTITY sklopAND IS PORT(
	a,b:IN std_logic;
	y:OUT std_logic );
END sklopAND;

ARCHITECTURE arch of sklopAND IS
BEGIN
	y<=a AND b;
END arch;

Structural_AND_OR_AND/sklopOR.vhdl
library IEEE;
use IEEE.std_logic_1164.all;

ENTITY sklopOR IS PORT(
	a,b:IN std_logic;
	y:OUT std_logic );
END sklopOR;

ARCHITECTURE arch of sklopOR IS
BEGIN
	y <= a OR b;
END arch;

Structural_AND_OR_AND/AND_OR_AND.vhdl
library IEEE;
use IEEE.std_logic_1164.all;

ENTITY and_or_and IS PORT(
	a,b,c,d:IN std_logic;
	y:OUT std_logic);
END and_or_and;

ARCHITECTURE arch OF and_or_and IS
	SIGNAL t1, t2 : std_logic;
BEGIN
	e1:ENTITY work.sklopAND port map (a => a, b => b, y => t1);
	e2:ENTITY work.sklopOR port map(a => t1, b => c, y => t2);
	e3:ENTITY work.sklopAND port map (a => t2, b => d, y => y);
END arch;

Structural_AND_OR_AND/tb.vhdl
library IEEE;
use IEEE.std_logic_1164.all;

ENTITY tb IS
END tb;

ARCHITECTURE arch OF tb IS
	COMPONENT AND_OR_AND
	PORT(
		a,b,c,d:IN std_logic;
		y:OUT std_logic);
	END COMPONENT;

	

	SIGNAL a,b,y,c,d : std_logic;
BEGIN
	sklop_and_or_and : AND_OR_AND port map(a => a, b => b, c => c, d => d, y => y);

	PROCESS BEGIN
		a <= 'X';
		b <= 'X';
		c <= 'X';
		d <= 'X';
		wait for 1 ns;

		a <= '0';
		b <= '0';
		c <= '0';
		d <= '0';
		wait for 1 ns;
		
		a <= '0';
		b <= '0';
		c <= '0';
		d <= '1';
		wait for 1 ns;
		
		a <= '0';
		b <= '0';
		c <= '1';
		d <= '0';
		wait for 1 ns;
		
		a <= '0';
		b <= '0';
		c <= '1';
		d <= '1';
		wait for 1 ns;
		
		a <= '0';
		b <= '1';
		c <= '0';
		d <= '0';
		wait for 1 ns;
		
		a <= '0';
		b <= '1';
		c <= '0';
		d <= '1';
		wait for 1 ns;
		
		a <= '0';
		b <= '1';
		c <= '1';
		d <= '0';
		wait for 1 ns;
		
		a <= '0';
		b <= '1';
		c <= '1';
		d <= '1';
		wait for 1 ns;
		
		a <= '1';
		b <= '0';
		c <= '0';
		d <= '0';
		wait for 1 ns;
		
		a <= '1';
		b <= '0';
		c <= '0';
		d <= '1';
		wait for 1 ns;
		
		a <= '1';
		b <= '0';
		c <= '1';
		d <= '0';
		wait for 1 ns;
		
		a <= '1';
		b <= '0';
		c <= '1';
		d <= '1';
		wait for 1 ns;
	
		a <= '1';
		b <= '1';
		c <= '0';
		d <= '0';
		wait for 1 ns;
		
		a <= '1';
		b <= '1';
		c <= '0';
		d <= '1';
		wait for 1 ns;
			
		a <= '1';
		b <= '1';
		c <= '1';
		d <= '0';
		wait for 1 ns;
		
		a <= '1';
		b <= '1';
		c <= '1';
		d <= '1';
		wait for 1 ns;
		
		assert false report "End of test";
		WAIT;
	END PROCESS;
END arch;

Structural_AND_OR_AND/waveform.vcd
$date
  Tue Apr 09 15:15:16 2019
$end
$version
  GHDL v0
$end
$timescale
  1 fs
$end
$scope module standard $end
$upscope $end
$scope module std_logic_1164 $end
$upscope $end
$scope module tb $end
$var reg 1 ! a $end
$var reg 1 " b $end
$var reg 1 # y $end
$var reg 1 $ c $end
$var reg 1 % d $end
$scope module sklop_and_or_and $end
$var reg 1 & a $end
$var reg 1 ' b $end
$var reg 1 ( c $end
$var reg 1 ) d $end
$var reg 1 * y $end
$var reg 1 + t1 $end
$var reg 1 , t2 $end
$scope module e1 $end
$var reg 1 - a $end
$var reg 1 . b $end
$var reg 1 / y $end
$upscope $end
$scope module e2 $end
$var reg 1 0 a $end
$var reg 1 1 b $end
$var reg 1 2 y $end
$upscope $end
$scope module e3 $end
$var reg 1 3 a $end
$var reg 1 4 b $end
$var reg 1 5 y $end
$upscope $end
$upscope $end
$upscope $end
$enddefinitions $end
#0
X!
X"
X#
X$
X%
X&
X'
X(
X)
X*
X+
X,
X-
X.
X/
X0
X1
X2
X3
X4
X5
#1000000
0!
0"
0#
0$
0%
0&
0'
0(
0)
0*
0+
0,
0-
0.
0/
00
01
02
03
04
05
#2000000
1%
1)
14
#3000000
1$
0%
1(
0)
1,
11
12
13
04
#4000000
1#
1%
1)
1*
14
15
#5000000
1"
0#
0$
0%
1'
0(
0)
0*
0,
1.
01
02
03
04
05
#6000000
1%
1)
14
#7000000
1$
0%
1(
0)
1,
11
12
13
04
#8000000
1#
1%
1)
1*
14
15
#9000000
1!
0"
0#
0$
0%
1&
0'
0(
0)
0*
0,
1-
0.
01
02
03
04
05
#10000000
1%
1)
14
#11000000
1$
0%
1(
0)
1,
11
12
13
04
#12000000
1#
1%
1)
1*
14
15
#13000000
1"
0#
0$
0%
1'
0(
0)
0*
1+
1,
1.
1/
10
01
12
13
04
05
#14000000
1#
1%
1)
1*
14
15
#15000000
0#
1$
0%
1(
0)
0*
11
04
05
#16000000
1#
1%
1)
1*
14
15
