JK_counter_up_2_bist/and.vhdl
library IEEE;
use IEEE.STD_LOGIC_1164.ALL;

ENTITY and_sklop IS PORT
(
	A,B : IN STD_LOGIC;
	Y : OUT STD_LOGIC
);
END and_sklop;


ARCHITECTURE arch OF and_sklop IS
BEGIN
	Y <= A and B;
END arch;

JK_counter_up_2_bist/JK_brojilo.vhdl
library IEEE;
use IEEE.STD_LOGIC_1164.ALL;

ENTITY JK IS PORT
(
	clk,J,K, reset : IN STD_LOGIC;
	Q, nQ : OUT STD_LOGIC
);
END JK;


ARCHITECTURE arch OF JK IS
	SIGNAL Qtemp : std_logic := '0';	
	SIGNAL nQtemp : std_logic := '1';
BEGIN
	Q <= Qtemp;
	nQ <= nQtemp;

	PROCESS(clk, reset)
	BEGIN

		if(reset = '1') then
			Qtemp <= '0';
			nQtemp <= '1';
		end if;

		if(rising_edge(clk)) then
			if(J = '0' and K = '0') then
				NULL;
			elsif(J = '1' and K = '0') then
				Qtemp <= '1';
				nQtemp <= '0';
			elsif(J = '0' and K = '1') then
				Qtemp <= '0';
				nQtemp <= '1';
			elsif(J = '1' and K = '1') then
				Qtemp <= not Qtemp;
				nQtemp <= not nQtemp;
			end if;
		end if;
	END PROCESS;
END arch;

JK_counter_up_2_bist/brojilo_gore.vhdl
library IEEE;
use IEEE.STD_LOGIC_1164.ALL;

ENTITY brojilo IS PORT
(
	CLK : IN STD_LOGIC;
	out_put, out_put_N : OUT STD_LOGIC
);
END brojilo;

ARCHITECTURE arch OF brojilo IS 
	SIGNAL int_signal_clk : std_logic;
	SIGNAL int_signal_and : std_logic := '0';
	SIGNAL output_and : std_logic;
BEGIN
	jk1 : ENTITY work.JK port map(CLK => CLK, J => '1', K => '1', Q => out_put, nQ => int_signal_clk, reset =>output_and);
	jk2 : ENTITY work.JK port map(CLK => int_signal_clk, J => '1', K => '1', Q => out_put_N, nQ => int_signal_and, reset => output_and);

	and_sklop : ENTITY work.and_sklop port map(A => int_signal_and, B => '0', Y => output_and);
END arch;

JK_counter_up_2_bist/tb.vhdl
library IEEE;
use IEEE.STD_LOGIC_1164.ALL;

ENTITY tb IS
END tb;

ARCHITECTURE arch OF tb IS
	SIGNAL CLK : std_logic := '0';
	SIGNAL out_put, out_put_N : std_logic;
	CONSTANT clk_period : time := 1 ns;
	CONSTANT max_counter : integer := 10;
BEGIN
	UUT : ENTITY work.brojilo port map(CLK => CLK, out_put => out_put, out_put_N => out_put_N);

	clk_process : PROCESS
		VARIABLE counter : integer := 0;
	BEGIN
		while(counter < 10) loop
			CLK <= '0';
			wait for clk_period/2;
			CLK <= '1';
			wait for clk_period/2;
			counter := counter +1;
			if(counter = 9) then
				assert false report "End of test";
				wait;
			end if;
 
		end loop;
	END PROCESS;



END arch;

JK_counter_up_2_bist/wave.vcd
$date
  Fri Apr 26 16:22:19 2019
$end
$version
  GHDL v0
$end
$timescale
  1 fs
$end
$scope module standard $end
$upscope $end
$scope module std_logic_1164 $end
$upscope $end
$scope module tb $end
$var reg 1 ! clk $end
$var reg 1 " out_put $end
$var reg 1 # out_put_n $end
$scope module uut $end
$var reg 1 $ clk $end
$var reg 1 % out_put $end
$var reg 1 & out_put_n $end
$var reg 1 ' int_signal_clk $end
$var reg 1 ( int_signal_and $end
$var reg 1 ) output_and $end
$scope module jk1 $end
$var reg 1 * clk $end
$var reg 1 + j $end
$var reg 1 , k $end
$var reg 1 - reset $end
$var reg 1 . q $end
$var reg 1 / nq $end
$var reg 1 0 qtemp $end
$var reg 1 1 nqtemp $end
$upscope $end
$scope module jk2 $end
$var reg 1 2 clk $end
$var reg 1 3 j $end
$var reg 1 4 k $end
$var reg 1 5 reset $end
$var reg 1 6 q $end
$var reg 1 7 nq $end
$var reg 1 8 qtemp $end
$var reg 1 9 nqtemp $end
$upscope $end
$scope module and_sklop $end
$var reg 1 : a $end
$var reg 1 ; b $end
$var reg 1 < y $end
$upscope $end
$upscope $end
$upscope $end
$enddefinitions $end
#0
0!
0"
0#
0$
0%
0&
1'
1(
0)
0*
1+
1,
0-
0.
1/
00
11
12
13
14
05
06
17
08
19
1:
0;
0<
#500000
1!
1"
1$
1%
0'
1*
1.
0/
10
01
02
#1000000
0!
0$
0*
#1500000
1!
0"
1#
1$
0%
1&
1'
0(
1*
0.
1/
00
11
12
16
07
18
09
0:
#2000000
0!
0$
0*
#2500000
1!
1"
1$
1%
0'
1*
1.
0/
10
01
02
#3000000
0!
0$
0*
#3500000
1!
0"
0#
1$
0%
0&
1'
1(
1*
0.
1/
00
11
12
06
17
08
19
1:
#4000000
0!
0$
0*
#4500000
1!
1"
1$
1%
0'
1*
1.
0/
10
01
02
#5000000
0!
0$
0*
#5500000
1!
0"
1#
1$
0%
1&
1'
0(
1*
0.
1/
00
11
12
16
07
18
09
0:
#6000000
0!
0$
0*
#6500000
1!
1"
1$
1%
0'
1*
1.
0/
10
01
02
#7000000
0!
0$
0*
#7500000
1!
0"
0#
1$
0%
0&
1'
1(
1*
0.
1/
00
11
12
06
17
08
19
1:
#8000000
0!
0$
0*
#8500000
1!
1"
1$
1%
0'
1*
1.
0/
10
01
02
