D bistabil set_reset v2/d_bistabil_set_reset_v2.vhdl
library IEEE;
use IEEE.std_logic_1164.all;

ENTITY d_bistabil_set_reset_v2 IS PORT
(
	D,S,R,CP : IN std_logic;
	Q, nQ : OUT std_logic);
END d_bistabil_set_reset_v2;

ARCHITECTURE arch OF d_bistabil_set_reset_v2 IS 
BEGIN
	PROCESS(CP, S)
		VARIABLE stanje : std_logic := '0';
	BEGIN
		IF S = '1' THEN
			stanje := '1';
		ELSIF falling_edge(CP) THEN
			IF R = '1' THEN
				stanje := '0';
			ELSE
				stanje := D;
			END IF;
		END IF;

		Q <= stanje;
		nQ <= not stanje;
	END PROCESS;
END arch;

D bistabil set_reset v2/tb.vhdl
library IEEE;
use IEEE.std_logic_1164.all;

ENTITY tb IS
END tb;


ARCHITECTURE arch OF tb IS
	COMPONENT d_bistabil_set_reset_v2 
	PORT
	(
		D,S,R,CP : IN std_logic;
		Q, nQ : OUT std_logic);
	END COMPONENT;

	SIGNAL D,S,R,CP,Q,nQ : std_logic;
BEGIN 
	d_bist : d_bistabil_set_reset_v2 port map(D => D, S => S, R => R, CP => CP, Q => Q, nQ => nQ);

	PROCESS
	BEGIN
		CP <= 'X';
		D <= 'X';
		S <= 'X';
		R <= 'X';
		wait for 1 ns;

		CP <= '0';
		D <= '0';
		S <= '0';
		R <= '0';
		wait for 1 ns;
		
		CP <= '0';
		D <= '0';
		S <= '0';
		R <= '1';
		wait for 1 ns;
		
		CP <= '0';
		D <= '0';
		S <= '1';
		R <= '0';
		wait for 1 ns;
		
		CP <= '0';
		D <= '0';
		S <= '1';
		R <= '1';
		wait for 1 ns;
		
		CP <= '0';
		D <= '1';
		S <= '0';
		R <= '0';
		wait for 1 ns;
		
		CP <= '0';
		D <= '1';
		S <= '0';
		R <= '1';
		wait for 1 ns;
		
		CP <= '0';
		D <= '1';
		S <= '1';
		R <= '0';
		wait for 1 ns;
		
		CP <= '0';
		D <= '1';
		S <= '1';
		R <= '1';
		wait for 1 ns;
		
		CP <= '1';
		D <= '0';
		S <= '0';
		R <= '0';
		wait for 1 ns;
		
		CP <= '1';
		D <= '0';
		S <= '0';
		R <= '1';
		wait for 1 ns;
		
		CP <= '1';
		D <= '0';
		S <= '1';
		R <= '0';
		wait for 1 ns;
		
		CP <= '1';
		D <= '0';
		S <= '1';
		R <= '1';
		wait for 1 ns;
		
		CP <= '1';
		D <= '1';
		S <= '0';
		R <= '0';
		wait for 1 ns;
		
		CP <= '1';
		D <= '1';
		S <= '0';
		R <= '1';
		wait for 1 ns;
		
		CP <= '1';
		D <= '1';
		S <= '1';
		R <= '0';
		wait for 1 ns;

		CP <= '1';
		D <= '1';
		S <= '1';
		R <= '1';
		wait for 1 ns;

		CP <= '0';
		D <= '1';
		S <= '0';
		R <= '0';
		wait for 1 ns;
		
		CP <= '1';
		D <= '1';
		S <= '0';
		R <= '0';
		wait for 1 ns;
		
		CP <= '0';
		D <= '0';
		S <= '0';
		R <= '0';
		wait for 1 ns;

		CP <= '1';
		D <= '0';
		S <= '0';
		R <= '0';
		wait for 1 ns;

		CP <= '0';
		D <= '1';
		S <= '0';
		R <= '1';
		wait for 1 ns;
		
		assert false report "End of test";
		WAIT;
	END PROCESS;
END arch;

D bistabil set_reset v2/waveform.vcd
$date
  Fri Apr 19 13:00:35 2019
$end
$version
  GHDL v0
$end
$timescale
  1 fs
$end
$scope module standard $end
$upscope $end
$scope module std_logic_1164 $end
$upscope $end
$scope module tb $end
$var reg 1 ! d $end
$var reg 1 " s $end
$var reg 1 # r $end
$var reg 1 $ cp $end
$var reg 1 % q $end
$var reg 1 & nq $end
$scope module d_bist $end
$var reg 1 ' d $end
$var reg 1 ( s $end
$var reg 1 ) r $end
$var reg 1 * cp $end
$var reg 1 + q $end
$var reg 1 , nq $end
$upscope $end
$upscope $end
$enddefinitions $end
#0
X!
X"
X#
X$
0%
1&
X'
X(
X)
X*
0+
1,
#1000000
0!
0"
0#
0$
0'
0(
0)
0*
#2000000
1#
1)
#3000000
1"
0#
1%
0&
1(
0)
1+
0,
#4000000
1#
1)
#5000000
1!
0"
0#
1'
0(
0)
#6000000
1#
1)
#7000000
1"
0#
1(
0)
#8000000
1#
1)
#9000000
0!
0"
0#
1$
0'
0(
0)
1*
#10000000
1#
1)
#11000000
1"
0#
1(
0)
#12000000
1#
1)
#13000000
1!
0"
0#
1'
0(
0)
#14000000
1#
1)
#15000000
1"
0#
1(
0)
#16000000
1#
1)
#17000000
0"
0#
0$
0(
0)
0*
#18000000
1$
1*
#19000000
0!
0$
0%
1&
0'
0*
0+
1,
#20000000
1$
1*
#21000000
1!
1#
0$
1'
1)
0*
