MUX21/mux_21.vhdl
library IEEE;
use IEEE.std_logic_1164.all;

ENTITY mux_21 IS PORT(
	a, e, x, z: IN std_logic;
	y:OUT std_logic);
END mux_21;

ARCHITECTURE arch OF mux_21 IS
BEGIN
PROCESS(a,e,x,z)
BEGIN
	y <= '0';
	if e = '0' then
		y <= '0';
	elsif e = '1' then
		if a = '0' then
			y <= x;
		elsif a = '1' then
		 	y <= z;
		end if;
	end if;
END PROCESS;
END arch;

MUX21/tb.vhdl
library IEEE;
use IEEE.std_logic_1164.all;

ENTITY tb IS
END tb;

ARCHITECTURE arch OF tb IS
	COMPONENT mux_21
	PORT(
		a, e, x, z: IN std_logic;
		y:OUT std_logic);
	END COMPONENT;

	SIGNAL a,e,x,z,y:std_logic;
BEGIN
	mux:mux_21 port map (a => a, e => e, x => x, z => z, y => y);

	PROCESS BEGIN
		a <= 'X';
		e <= 'X';
		x <= 'X';
		z <= 'X';
		wait for 1 ns;

		a <= '0';
		e <= '0';
		x <= '0';
		z <= '0';
		wait for 1 ns;
		
		a <= '0';
		e <= '0';
		x <= '0';
		z <= '1';
		wait for 1 ns;
		
		a <= '0';
		e <= '0';
		x <= '1';
		z <= '0';
		wait for 1 ns;
		
		a <= '0';
		e <= '0';
		x <= '1';
		z <= '1';
		wait for 1 ns;
		
		a <= '0';
		e <= '1';
		x <= '0';
		z <= '0';
		wait for 1 ns;
		
		a <= '0';
		e <= '1';
		x <= '0';
		z <= '1';
		wait for 1 ns;

		a <= '0';
		e <= '1';
		x <= '1';
		z <= '0';
		wait for 1 ns;
		
		a <= '0';
		e <= '1';
		x <= '1';
		z <= '1';
		wait for 1 ns;
		
		a <= '1';
		e <= '0';
		x <= '0';
		z <= '0';
		wait for 1 ns;
		
		a <= '1';
		e <= '0';
		x <= '0';
		z <= '1';
		wait for 1 ns;
		
		a <= '1';
		e <= '0';
		x <= '1';
		z <= '0';
		wait for 1 ns;

		a <= '1';
		e <= '0';
		x <= '1';
		z <= '1';
		wait for 1 ns;
		
		a <= '1';
		e <= '1';
		x <= '0';
		z <= '0';
		wait for 1 ns;
		
		a <= '1';
		e <= '1';
		x <= '0';
		z <= '1';
		wait for 1 ns;
		
		a <= '1';
		e <= '1';
		x <= '1';
		z <= '0';
		wait for 1 ns;

		a <= '1';
		e <= '1';
		x <= '1';
		z <= '1';
		wait for 1 ns;

		ASSERT FALSE REPORT "End of test";
		WAIT;
	END PROCESS;
END arch;

MUX21/waveform.vcd
$date
  Mon Apr 15 13:31:36 2019
$end
$version
  GHDL v0
$end
$timescale
  1 fs
$end
$scope module standard $end
$upscope $end
$scope module std_logic_1164 $end
$upscope $end
$scope module tb $end
$var reg 1 ! a $end
$var reg 1 " e $end
$var reg 1 # x $end
$var reg 1 $ z $end
$var reg 1 % y $end
$scope module mux $end
$var reg 1 & a $end
$var reg 1 ' e $end
$var reg 1 ( x $end
$var reg 1 ) z $end
$var reg 1 * y $end
$upscope $end
$upscope $end
$enddefinitions $end
#0
X!
X"
X#
X$
0%
X&
X'
X(
X)
0*
#1000000
0!
0"
0#
0$
0&
0'
0(
0)
#2000000
1$
1)
#3000000
1#
0$
1(
0)
#4000000
1$
1)
#5000000
1"
0#
0$
1'
0(
0)
#6000000
1$
1)
#7000000
1#
0$
1%
1(
0)
1*
#8000000
1$
1)
1*
#9000000
1!
0"
0#
0$
0%
1&
0'
0(
0)
0*
#10000000
1$
1)
#11000000
1#
0$
1(
0)
#12000000
1$
1)
#13000000
1"
0#
0$
1'
0(
0)
#14000000
1$
1%
1)
1*
#15000000
1#
0$
0%
1(
0)
0*
#16000000
1$
1%
1)
1*
