T_bist_0360/T.vhdl
library ieee;
use ieee.std_logic_1164.all;

ENTITY T_bist IS PORT
(
	T, clk : IN std_logic := '0';
	Q, nQ : OUT std_logic := '0'
);
END T_bist;

ARCHITECTURE arch OF T_bist IS
	SIGNAL tempQ : std_logic := '0';
	SIGNAL tempQn : std_logic := '1';
BEGIN
	Q <= tempQ;
	nQ <= tempQn;

	PROCESS(clk)
	BEGIN
		if(rising_edge(clk)) then
			if(T = '0') then
				tempQ <= tempQ;
				tempQn <= tempQn;
			else
				tempQ <= not tempQ;
				tempQn <= not tempQn;		
			end if;
		end if;
	END PROCESS;
END arch;

T_bist_0360/brojilo.vhdl
library ieee;
use ieee.std_logic_1164.all;

ENTITY brojilo IS PORT
(
	clk : IN std_logic := '0';
	Q : OUT std_logic_vector(2 downto 0) := "000";
	nQ : OUT std_logic_vector(2 downto 0) := "111"
);
END brojilo;

ARCHITECTURE arch OF brojilo IS
	SIGNAL tempQ : std_logic_vector(2 downto 0) := "000";
	SIGNAL tempQn : std_logic_vector(2 downto 0) := "111";
BEGIN
	Q <= tempQ;
	nQ <= tempQn;

	b0 : ENTITY work.T_bist port map(T => tempQn(2), clk => clk, Q => tempQ(0), nQ => tempQn(0));
	b1 : ENTITY work.T_bist port map(T => tempQn(0), clk => clk, Q => tempQ(1), nQ => tempQn(1));
	b2 : ENTITY work.T_bist port map(T => tempQ(1), clk => clk, Q => tempQ(2), nQ => tempQn(2));
END arch;

T_bist_0360/VHDL/tb.vhdl
library ieee;
use ieee.std_logic_1164.all;

ENTITY tb IS
END tb;

ARCHITECTURE arch OF tb IS
	SIGNAL clk : std_logic := '0';
	SIGNAL Q : std_logic_vector(2 downto 0) := "000";
	SIGNAL nQ : std_logic_vector(2 downto 0) := "111";

	CONSTANT clk_period : time := 1 ns;
BEGIN
	UUT : ENTITY work.brojilo port map(clk => clk, Q => Q, nQ => nQ);

	clk_proc : PROCESS
		VARIABLE counter : integer := 0;
	BEGIN
		if(counter <= 30) then
			clk <= '0';
			wait for clk_period/2;
			clk <= '1';
			wait for clk_period/2;
			counter := counter + 1;
		else
			assert false report "End of test";
			wait;
		end if; 
	END PROCESS;
END arch;

T_bist_0360/wave.vcd
$date
  Wed May 29 13:53:31 2019
$end
$version
  GHDL v0
$end
$timescale
  1 fs
$end
$scope module standard $end
$upscope $end
$scope module std_logic_1164 $end
$upscope $end
$scope module tb $end
$var reg 1 ! clk $end
$var reg 3 " q[2:0] $end
$var reg 3 # nq[2:0] $end
$scope module uut $end
$var reg 1 $ clk $end
$var reg 3 % q[2:0] $end
$var reg 3 & nq[2:0] $end
$var reg 3 ' tempq[2:0] $end
$var reg 3 ( tempqn[2:0] $end
$scope module b0 $end
$var reg 1 ) t $end
$var reg 1 * clk $end
$var reg 1 + q $end
$var reg 1 , nq $end
$var reg 1 - tempq $end
$var reg 1 . tempqn $end
$upscope $end
$scope module b1 $end
$var reg 1 / t $end
$var reg 1 0 clk $end
$var reg 1 1 q $end
$var reg 1 2 nq $end
$var reg 1 3 tempq $end
$var reg 1 4 tempqn $end
$upscope $end
$scope module b2 $end
$var reg 1 5 t $end
$var reg 1 6 clk $end
$var reg 1 7 q $end
$var reg 1 8 nq $end
$var reg 1 9 tempq $end
$var reg 1 : tempqn $end
$upscope $end
$upscope $end
$upscope $end
$enddefinitions $end
#0
0!
b000 "
b111 #
0$
b000 %
b111 &
b000 '
b111 (
1)
0*
0+
1,
0-
1.
1/
00
01
12
03
14
05
06
07
18
09
1:
#500000
1!
b011 "
b100 #
1$
b011 %
b100 &
b011 '
b100 (
1*
1+
0,
1-
0.
0/
10
11
02
13
04
15
16
#1000000
0!
0$
0*
00
06
#1500000
1!
b110 "
b001 #
1$
b110 %
b001 &
b110 '
b001 (
0)
1*
0+
1,
0-
1.
1/
10
16
17
08
19
0:
#2000000
0!
0$
0*
00
06
#2500000
1!
b000 "
b111 #
1$
b000 %
b111 &
b000 '
b111 (
1)
1*
10
01
12
03
14
05
16
07
18
09
1:
#3000000
0!
0$
0*
00
06
#3500000
1!
b011 "
b100 #
1$
b011 %
b100 &
b011 '
b100 (
1*
1+
0,
1-
0.
0/
10
11
02
13
04
15
16
#4000000
0!
0$
0*
00
06
#4500000
1!
b110 "
b001 #
1$
b110 %
b001 &
b110 '
b001 (
0)
1*
0+
1,
0-
1.
1/
10
16
17
08
19
0:
#5000000
0!
0$
0*
00
06
#5500000
1!
b000 "
b111 #
1$
b000 %
b111 &
b000 '
b111 (
1)
1*
10
01
12
03
14
05
16
07
18
09
1:
#6000000
0!
0$
0*
00
06
#6500000
1!
b011 "
b100 #
1$
b011 %
b100 &
b011 '
b100 (
1*
1+
0,
1-
0.
0/
10
11
02
13
04
15
16
#7000000
0!
0$
0*
00
06
#7500000
1!
b110 "
b001 #
1$
b110 %
b001 &
b110 '
b001 (
0)
1*
0+
1,
0-
1.
1/
10
16
17
08
19
0:
#8000000
0!
0$
0*
00
06
#8500000
1!
b000 "
b111 #
1$
b000 %
b111 &
b000 '
b111 (
1)
1*
10
01
12
03
14
05
16
07
18
09
1:
#9000000
0!
0$
0*
00
06
#9500000
1!
b011 "
b100 #
1$
b011 %
b100 &
b011 '
b100 (
1*
1+
0,
1-
0.
0/
10
11
02
13
04
15
16
#10000000
0!
0$
0*
00
06
#10500000
1!
b110 "
b001 #
1$
b110 %
b001 &
b110 '
b001 (
0)
1*
0+
1,
0-
1.
1/
10
16
17
08
19
0:
#11000000
0!
0$
0*
00
06
#11500000
1!
b000 "
b111 #
1$
b000 %
b111 &
b000 '
b111 (
1)
1*
10
01
12
03
14
05
16
07
18
09
1:
#12000000
0!
0$
0*
00
06
#12500000
1!
b011 "
b100 #
1$
b011 %
b100 &
b011 '
b100 (
1*
1+
0,
1-
0.
0/
10
11
02
13
04
15
16
#13000000
0!
0$
0*
00
06
#13500000
1!
b110 "
b001 #
1$
b110 %
b001 &
b110 '
b001 (
0)
1*
0+
1,
0-
1.
1/
10
16
17
08
19
0:
#14000000
0!
0$
0*
00
06
#14500000
1!
b000 "
b111 #
1$
b000 %
b111 &
b000 '
b111 (
1)
1*
10
01
12
03
14
05
16
07
18
09
1:
#15000000
0!
0$
0*
00
06
#15500000
1!
b011 "
b100 #
1$
b011 %
b100 &
b011 '
b100 (
1*
1+
0,
1-
0.
0/
10
11
02
13
04
15
16
#16000000
0!
0$
0*
00
06
#16500000
1!
b110 "
b001 #
1$
b110 %
b001 &
b110 '
b001 (
0)
1*
0+
1,
0-
1.
1/
10
16
17
08
19
0:
#17000000
0!
0$
0*
00
06
#17500000
1!
b000 "
b111 #
1$
b000 %
b111 &
b000 '
b111 (
1)
1*
10
01
12
03
14
05
16
07
18
09
1:
#18000000
0!
0$
0*
00
06
#18500000
1!
b011 "
b100 #
1$
b011 %
b100 &
b011 '
b100 (
1*
1+
0,
1-
0.
0/
10
11
02
13
04
15
16
#19000000
0!
0$
0*
00
06
#19500000
1!
b110 "
b001 #
1$
b110 %
b001 &
b110 '
b001 (
0)
1*
0+
1,
0-
1.
1/
10
16
17
08
19
0:
#20000000
0!
0$
0*
00
06
#20500000
1!
b000 "
b111 #
1$
b000 %
b111 &
b000 '
b111 (
1)
1*
10
01
12
03
14
05
16
07
18
09
1:
#21000000
0!
0$
0*
00
06
#21500000
1!
b011 "
b100 #
1$
b011 %
b100 &
b011 '
b100 (
1*
1+
0,
1-
0.
0/
10
11
02
13
04
15
16
#22000000
0!
0$
0*
00
06
#22500000
1!
b110 "
b001 #
1$
b110 %
b001 &
b110 '
b001 (
0)
1*
0+
1,
0-
1.
1/
10
16
17
08
19
0:
#23000000
0!
0$
0*
00
06
#23500000
1!
b000 "
b111 #
1$
b000 %
b111 &
b000 '
b111 (
1)
1*
10
01
12
03
14
05
16
07
18
09
1:
#24000000
0!
0$
0*
00
06
#24500000
1!
b011 "
b100 #
1$
b011 %
b100 &
b011 '
b100 (
1*
1+
0,
1-
0.
0/
10
11
02
13
04
15
16
#25000000
0!
0$
0*
00
06
#25500000
1!
b110 "
b001 #
1$
b110 %
b001 &
b110 '
b001 (
0)
1*
0+
1,
0-
1.
1/
10
16
17
08
19
0:
#26000000
0!
0$
0*
00
06
#26500000
1!
b000 "
b111 #
1$
b000 %
b111 &
b000 '
b111 (
1)
1*
10
01
12
03
14
05
16
07
18
09
1:
#27000000
0!
0$
0*
00
06
#27500000
1!
b011 "
b100 #
1$
b011 %
b100 &
b011 '
b100 (
1*
1+
0,
1-
0.
0/
10
11
02
13
04
15
16
#28000000
0!
0$
0*
00
06
#28500000
1!
b110 "
b001 #
1$
b110 %
b001 &
b110 '
b001 (
0)
1*
0+
1,
0-
1.
1/
10
16
17
08
19
0:
#29000000
0!
0$
0*
00
06
#29500000
1!
b000 "
b111 #
1$
b000 %
b111 &
b000 '
b111 (
1)
1*
10
01
12
03
14
05
16
07
18
09
1:
#30000000
0!
0$
0*
00
06
#30500000
1!
b011 "
b100 #
1$
b011 %
b100 &
b011 '
b100 (
1*
1+
0,
1-
0.
0/
10
11
02
13
04
15
16
