SR bistabil behavioral/sr_bistabil_ponasajni.vhdl
library IEEE;
use IEEE.std_logic_1164.all;

ENTITY sr_bistabil_ponasajni IS PORT (
	S,R,CP: IN std_logic;
	Q,nQ : OUT std_logic);
END sr_bistabil_ponasajni;

ARCHITECTURE arch OF sr_bistabil_ponasajni IS
	SIGNAL intQ : std_logic := '0';
	SIGNAL intQn : std_logic := '1';
BEGIN
	PROCESS(S,R,CP)
		VARIABLE stanje : std_logic := '0';
	
	BEGIN
		if CP = '1' then
			stanje := S OR (intQ AND NOT(R));
		end if;

		Q <= stanje;
		nQ <= not stanje;

	END PROCESS;
END arch;

SR bistabil behavioral/tb.vhdl
library IEEE;
use IEEE.std_logic_1164.all;

ENTITY tb IS
END tb;

ARCHITECTURE arch OF tb IS
	COMPONENT sr_bistabil_ponasajni
	PORT(
		S,R,CP: IN std_logic;
		Q,nQ : OUT std_logic);
	END COMPONENT;

	SIGNAL S,R,CP,Q,nQ : std_logic;
BEGIN
	sr : sr_bistabil_ponasajni port map (S => S, R => R, CP => CP, Q => Q, nQ => nQ);

	PROCESS
	BEGIN
		S <= 'X';
		R <= 'X';
		CP <= 'X';
		wait for 1 ns;

		S <= '0';
		R <= '0';
		CP <= '0';
		wait for 1 ns;
		
		S <= '0';
		R <= '0';
		CP <= '1';
		wait for 1 ns;
		
		S <= '0';
		R <= '1';
		CP <= '0';
		wait for 1 ns;
		
		S <= '0';
		R <= '1';
		CP <= '1';
		wait for 1 ns;
		
		S <= '1';
		R <= '0';
		CP <= '0';
		wait for 1 ns;
		
		S <= '1';
		R <= '0';
		CP <= '1';
		wait for 1 ns;
		
		S <= '1';
		R <= '1';
		CP <= '0';
		wait for 1 ns;

		S <= '0';
		R <= '1';
		CP <= '1';
		wait for 1 ns;

		assert false report "End of test";
		wait;
	END PROCESS;
END arch;

SR bistabil behavioral/waveform.vcd
$date
  Wed Apr 17 09:53:23 2019
$end
$version
  GHDL v0
$end
$timescale
  1 fs
$end
$scope module standard $end
$upscope $end
$scope module std_logic_1164 $end
$upscope $end
$scope module tb $end
$var reg 1 ! s $end
$var reg 1 " r $end
$var reg 1 # cp $end
$var reg 1 $ q $end
$var reg 1 % nq $end
$scope module sr $end
$var reg 1 & s $end
$var reg 1 ' r $end
$var reg 1 ( cp $end
$var reg 1 ) q $end
$var reg 1 * nq $end
$var reg 1 + intq $end
$var reg 1 , intqn $end
$upscope $end
$upscope $end
$enddefinitions $end
#0
X!
X"
X#
0$
1%
X&
X'
X(
0)
1*
0+
1,
#1000000
0!
0"
0#
0&
0'
0(
#2000000
1#
1(
#3000000
1"
0#
1'
0(
#4000000
1#
1(
#5000000
1!
0"
0#
1&
0'
0(
#6000000
1#
1$
0%
1(
1)
0*
#7000000
1"
0#
1'
0(
#8000000
0!
1#
0$
1%
0&
1(
0)
1*
