T_counter_up_2_bist/and.vhdl
library ieee;
use ieee.std_logic_1164.all;

ENTITY and_sklop IS PORT
(
	A,B : IN std_logic;
	Y : OUT std_logic
);
END and_sklop;


ARCHITECTURE arch OF and_sklop IS 
BEGIN
	Y <= A and B;
END arch;

T_counter_up_2_bist/Tbist.vhdl
library ieee;
use ieee.std_logic_1164.all;

ENTITY Tbist IS PORT
(
	T,clk,reset : IN std_logic;
	Q,nQ : OUT std_logic
);
END Tbist;


ARCHITECTURE arch OF Tbist IS 
	SIGNAL Qtemp : std_logic :='0';
	SIGNAL nQtemp : std_logic :='1';
BEGIN
	Q <= Qtemp;
	nQ <= nQtemp;

	PROCESS(clk,reset)
	BEGIN
		if(reset = '1') then
			Qtemp <= '0';
			nQtemp <= '1';
		end if;

		if(rising_edge(clk)) then
			if(T = '0') then
				Qtemp <= Qtemp;
				nQtemp <= nQtemp;
			elsif(T = '1') then
				Qtemp <= not Qtemp;
				nQtemp <= not nQtemp;
			end if;
		end if;
	END PROCESS;
END arch;

T_counter_up_2_bist/brojilo.vhdl
library ieee;
use ieee.std_logic_1164.all;

ENTITY brojilo IS PORT
(
	clk : IN std_logic;
	output_B0, output_B1 : OUT std_logic
);
END brojilo;

ARCHITECTURE arch OF brojilo IS
	SIGNAL int_clk : std_logic;
	SIGNAL signal_for_and : std_logic;
	SIGNAL Y : std_logic;
BEGIN
	b0 : ENTITY work.Tbist port map(T => '1', clk => clk, reset => Y, Q => output_B0, nQ => int_clk);
	b1 : ENTITY work.Tbist port map(T => '1', clk => int_clk, reset => Y, Q => output_B1, nQ => signal_for_and);
	and_sklop : ENTITY work.and_sklop port map(A => signal_for_and, B => '0', Y => Y);
END arch;

T_counter_up_2_bist/tb.vhdl
library ieee;
use ieee.std_logic_1164.all;

ENTITY tb IS 
END tb;


ARCHITECTURE arch OF tb IS
	SIGNAL clk, output_B0, output_B1 : std_logic;
	CONSTANT clk_period : time := 1 ns;
BEGIN
	UUT : ENTITY work.brojilo port map(clk => clk, output_B0 => output_B0, output_B1 => output_B1);

	clk_process : PROCESS
		VARIABLE counter : integer := 0;
	BEGIN
		if(counter < 10) then	
			clk <= '0';
			wait for clk_period/2;
			clk <= '1';
			wait for clk_period/2;
			counter := counter + 1;
		
		else 
			assert false report "End of test";
		wait;
		end if;
	END PROCESS;
END arch;

T_counter_up_2_bist/wave.vcd
$date
  Mon Apr 29 16:37:29 2019
$end
$version
  GHDL v0
$end
$timescale
  1 fs
$end
$scope module standard $end
$upscope $end
$scope module std_logic_1164 $end
$upscope $end
$scope module tb $end
$var reg 1 ! clk $end
$var reg 1 " output_b0 $end
$var reg 1 # output_b1 $end
$scope module uut $end
$var reg 1 $ clk $end
$var reg 1 % output_b0 $end
$var reg 1 & output_b1 $end
$var reg 1 ' int_clk $end
$var reg 1 ( signal_for_and $end
$var reg 1 ) y $end
$scope module b0 $end
$var reg 1 * t $end
$var reg 1 + clk $end
$var reg 1 , reset $end
$var reg 1 - q $end
$var reg 1 . nq $end
$var reg 1 / qtemp $end
$var reg 1 0 nqtemp $end
$upscope $end
$scope module b1 $end
$var reg 1 1 t $end
$var reg 1 2 clk $end
$var reg 1 3 reset $end
$var reg 1 4 q $end
$var reg 1 5 nq $end
$var reg 1 6 qtemp $end
$var reg 1 7 nqtemp $end
$upscope $end
$scope module and_sklop $end
$var reg 1 8 a $end
$var reg 1 9 b $end
$var reg 1 : y $end
$upscope $end
$upscope $end
$upscope $end
$enddefinitions $end
#0
0!
0"
0#
0$
0%
0&
1'
1(
0)
1*
0+
0,
0-
1.
0/
10
11
12
03
04
15
06
17
18
09
0:
#500000
1!
1"
1$
1%
0'
1+
1-
0.
1/
00
02
#1000000
0!
0$
0+
#1500000
1!
0"
1#
1$
0%
1&
1'
0(
1+
0-
1.
0/
10
12
14
05
16
07
08
#2000000
0!
0$
0+
#2500000
1!
1"
1$
1%
0'
1+
1-
0.
1/
00
02
#3000000
0!
0$
0+
#3500000
1!
0"
0#
1$
0%
0&
1'
1(
1+
0-
1.
0/
10
12
04
15
06
17
18
#4000000
0!
0$
0+
#4500000
1!
1"
1$
1%
0'
1+
1-
0.
1/
00
02
#5000000
0!
0$
0+
#5500000
1!
0"
1#
1$
0%
1&
1'
0(
1+
0-
1.
0/
10
12
14
05
16
07
08
#6000000
0!
0$
0+
#6500000
1!
1"
1$
1%
0'
1+
1-
0.
1/
00
02
#7000000
0!
0$
0+
#7500000
1!
0"
0#
1$
0%
0&
1'
1(
1+
0-
1.
0/
10
12
04
15
06
17
18
#8000000
0!
0$
0+
#8500000
1!
1"
1$
1%
0'
1+
1-
0.
1/
00
02
#9000000
0!
0$
0+
#9500000
1!
0"
1#
1$
0%
1&
1'
0(
1+
0-
1.
0/
10
12
14
05
16
07
08
