D bistabil set_reset v1/d_bist_set_reset.vhdl
library IEEE;
use IEEE.std_logic_1164.all;

ENTITY d_bist_set_reset IS PORT
(
	D,CP,S,R : IN std_logic;
	Q, nQ : OUT std_logic);
END d_bist_set_reset;


ARCHITECTURE arch OF d_bist_set_reset IS
BEGIN
	PROCESS(CP, S, R)
		VARIABLE stanje : std_logic:='0';
	BEGIN
		IF R = '0' THEN
			stanje := '0';
		ELSIF S = '0' THEN
			stanje := '1';
		ELSIF falling_edge(CP) THEN
			stanje := D;
		END IF;

		Q <= stanje;
		nQ <= not stanje;
	END PROCESS;
END arch;

D bistabil set_reset v1/tb.vhdl
library IEEE;
use IEEE.std_logic_1164.all;

ENTITY tb IS
END tb;

ARCHITECTURE arch OF tb IS
	COMPONENT d_bist_set_reset 
	PORT
	(
		D,CP,S,R : IN std_logic;
		Q, nQ : OUT std_logic);
	END COMPONENT;

	SIGNAL D,CP,S,R,Q,nQ : std_logic;
BEGIN
	d_bist : d_bist_set_reset port map(D => D, CP => CP, S => S, R => R, Q => Q, nQ => nQ);

	PROCESS 
	BEGIN
		CP <= 'X';
		S <= 'X';
		R <= 'X';
		D <= 'X';
		wait for 1 ns;

		CP <= '0';
		S <= '0';
		R <= '0';
		D <= '0';
		wait for 1 ns;
		
		CP <= '0';
		S <= '0';
		R <= '0';
		D <= '1';
		wait for 1 ns;
		
		CP <= '0';
		S <= '0';
		R <= '1';
		D <= '0';
		wait for 1 ns;
		
		CP <= '0';
		S <= '0';
		R <= '1';
		D <= '1';
		wait for 1 ns;
		
		CP <= '0';
		S <= '1';
		R <= '0';
		D <= '0';
		wait for 1 ns;
		
		CP <= '0';
		S <= '1';
		R <= '0';
		D <= '1';
		wait for 1 ns;
		
		CP <= '0';
		S <= '1';
		R <= '1';
		D <= '0';
		wait for 1 ns;
		
		CP <= '0';
		S <= '1';
		R <= '1';
		D <= '1';
		wait for 1 ns;
		
		CP <= '1';
		S <= '0';
		R <= '0';
		D <= '0';
		wait for 1 ns;

		CP <= '1';
		S <= '0';
		R <= '0';
		D <= '1';
		wait for 1 ns;
		
		CP <= '1';
		S <= '0';
		R <= '1';
		D <= '0';
		wait for 1 ns;
		
		CP <= '1';
		S <= '0';
		R <= '1';
		D <= '1';
		wait for 1 ns;
		
		CP <= '1';
		S <= '1';
		R <= '0';
		D <= '0';
		wait for 1 ns;
		
		CP <= '1';
		S <= '1';
		R <= '0';
		D <= '1';
		wait for 1 ns;
		
		CP <= '1';
		S <= '1';
		R <= '1';
		D <= '0';
		wait for 1 ns;
		
		CP <= '1';
		S <= '1';
		R <= '1';
		D <= '1';
		wait for 1 ns;

		CP <= '0';
		S <= '1';
		R <= '1';
		D <= '1';
		wait for 1 ns;

		CP <= '1';
		S <= '1';
		R <= '1';
		D <= '1';
		wait for 1 ns;

		assert false report"End of test";
		WAIT;
	END PROCESS;
END arch;

D bistabil set_reset v1/waveform.vcd
$date
  Fri Apr 19 12:36:17 2019
$end
$version
  GHDL v0
$end
$timescale
  1 fs
$end
$scope module standard $end
$upscope $end
$scope module std_logic_1164 $end
$upscope $end
$scope module tb $end
$var reg 1 ! d $end
$var reg 1 " cp $end
$var reg 1 # s $end
$var reg 1 $ r $end
$var reg 1 % q $end
$var reg 1 & nq $end
$scope module d_bist $end
$var reg 1 ' d $end
$var reg 1 ( cp $end
$var reg 1 ) s $end
$var reg 1 * r $end
$var reg 1 + q $end
$var reg 1 , nq $end
$upscope $end
$upscope $end
$enddefinitions $end
#0
X!
X"
X#
X$
0%
1&
X'
X(
X)
X*
0+
1,
#1000000
0!
0"
0#
0$
0'
0(
0)
0*
#2000000
1!
1'
#3000000
0!
1$
1%
0&
0'
1*
1+
0,
#4000000
1!
1'
#5000000
0!
1#
0$
0%
1&
0'
1)
0*
0+
1,
#6000000
1!
1'
#7000000
0!
1$
0'
1*
#8000000
1!
1'
#9000000
0!
1"
0#
0$
0'
1(
0)
0*
#10000000
1!
1'
#11000000
0!
1$
1%
0&
0'
1*
1+
0,
#12000000
1!
1'
#13000000
0!
1#
0$
0%
1&
0'
1)
0*
0+
1,
#14000000
1!
1'
#15000000
0!
1$
0'
1*
#16000000
1!
1'
#17000000
0"
1%
0&
0(
1+
0,
#18000000
1"
1(
