DEMUX21/demux.vhdl
library ieee;
use ieee.std_logic_1164.all;

ENTITY demux IS PORT
(
	data : IN std_logic := '0';
	address : IN std_logic := '0';
	enable : IN std_logic := '0';
	output_value : OUT std_logic_vector(1 downto 0)
);
END demux;

ARCHITECTURE arch OF demux IS

BEGIN
	PROCESS(data, address, enable)
	BEGIN
		if(enable = '1' ) then
			if(address = '0') then
				output_value(0) <= data;
			else 
				output_value(1) <= data; 
			end if;
		else
			output_value <= "XX";
		end if;
	END PROCESS;
END arch;

DEMUX21/tb.vhdl
library ieee;
use ieee.std_logic_1164.all;

ENTITY tb IS
END tb;

ARCHITECTURE arch OF tb IS
	SIGNAL data : std_logic := '0';
	SIGNAL address : std_logic := '0';
	SIGNAL enable : std_logic := '0';
	SIGNAL output_value : std_logic_vector(1 downto 0);
BEGIN
	UUT : ENTITY work.demux port map(data => data, address => address, enable => enable, output_value => output_value);

	stim_proc : PROCESS
	BEGIN
		enable <= '0';
		address <= '0';
		data <= '0';
		wait for 1 ns;

		enable <= '0';
		address <= '0';
		data <= '1';
		wait for 1 ns;
		
		enable <= '0';
		address <= '1';
		data <= '0';
		wait for 1 ns;
		
		enable <= '0';
		address <= '1';
		data <= '1';
		wait for 1 ns;
		
		enable <= '1';
		address <= '0';
		data <= '0';
		wait for 1 ns;
		
		enable <= '1';
		address <= '0';
		data <= '1';
		wait for 1 ns;
		
		enable <= '1';
		address <= '1';
		data <= '0';
		wait for 1 ns;
		
		enable <= '1';
		address <= '1';
		data <= '1';
		wait for 1 ns;

		assert false report "End of test";
		wait;
		
	END PROCESS;

END arch;

DEMUX21/wave.vcd
$date
  Tue May 28 09:38:37 2019
$end
$version
  GHDL v0
$end
$timescale
  1 fs
$end
$scope module standard $end
$upscope $end
$scope module std_logic_1164 $end
$upscope $end
$scope module tb $end
$var reg 1 ! data $end
$var reg 1 " address $end
$var reg 1 # enable $end
$var reg 2 $ output_value[1:0] $end
$scope module uut $end
$var reg 1 % data $end
$var reg 1 & address $end
$var reg 1 ' enable $end
$var reg 2 ( output_value[1:0] $end
$upscope $end
$upscope $end
$enddefinitions $end
#0
0!
0"
0#
bXX $
0%
0&
0'
bXX (
#1000000
1!
1%
#2000000
0!
1"
0%
1&
#3000000
1!
1%
#4000000
0!
0"
1#
bX0 $
0%
0&
1'
bX0 (
#5000000
1!
bX1 $
1%
bX1 (
#6000000
0!
1"
b01 $
0%
1&
b01 (
#7000000
1!
b11 $
1%
b11 (
