MUX21_revision/MUX.vhdl
library ieee;
use ieee.std_logic_1164.all;

ENTITY mux IS PORT
(
	data : IN std_logic_vector(1 downto 0);
	enable : IN std_logic := '0';
	address : IN std_logic := '0';
	out_value : OUT std_logic := '0'
);
END mux;

ARCHITECTURE arch OF mux IS

BEGIN
	PROCESS(data,enable,address)
	BEGIN
		if(enable = '1') then
			if(address = '0') then
				out_value <= data(0);
			else
				out_value <= data(1);
			end if;
		else
			out_value <= 'X';
		end if;
	END PROCESS;
END arch;

MUX21_revision/tb.vhdl
library ieee;
use ieee.std_logic_1164.all;

ENTITY tb IS
END tb;

ARCHITECTURE arch OF tb IS
	SIGNAL data : std_logic_vector(1 downto 0) := "00";
	SIGNAL enable : std_logic := '0';
	SIGNAL address : std_logic := '0';
	SIGNAL out_value : std_logic;
BEGIN
	UUT : ENTITY work.mux port map(data => data, enable => enable, address => address, out_value => out_value);

	stim_proc : PROCESS
	BEGIN	
		enable <= '0';
		data <= "00";
		address <= '0';
		wait for 1 ns;

		enable <= '0';
		data <= "01";
		address <= '0';
		wait for 1 ns;
		
		enable <= '0';
		data <= "10";
		address <= '0';
		wait for 1 ns;
		
		enable <= '0';
		data <= "11";
		address <= '0';
		wait for 1 ns;
		
		enable <= '0';
		data <= "00";
		address <= '1';
		wait for 1 ns;

		enable <= '0';
		data <= "01";
		address <= '0';
		wait for 1 ns;
		
		enable <= '0';
		data <= "10";
		address <= '0';
		wait for 1 ns;
		
		enable <= '0';
		data <= "11";
		address <= '0';
		wait for 1 ns;
		

		enable <= '1';
		data <= "00";
		address <= '0';
		wait for 1 ns;
		
		enable <= '1';
		data <= "01";
		address <= '0';
		wait for 1 ns;
		
		enable <= '1';
		data <= "10";
		address <= '0';
		wait for 1 ns;
		
		enable <= '1';
		data <= "11";
		address <= '0';
		wait for 1 ns;
		
		enable <= '1';
		data <= "00";
		address <= '1';
		wait for 1 ns;
		
		enable <= '1';
		data <= "01";
		address <= '1';
		wait for 1 ns;
		
		enable <= '1';
		data <= "10";
		address <= '1';
		wait for 1 ns;
		
		enable <= '1';
		data <= "11";
		address <= '1';
		wait for 1 ns;
		
		assert false report "End of test";
		wait;

	END PROCESS;

END arch;

MUX21_revision/wave.vcd
$date
  Tue May 28 09:29:10 2019
$end
$version
  GHDL v0
$end
$timescale
  1 fs
$end
$scope module standard $end
$upscope $end
$scope module std_logic_1164 $end
$upscope $end
$scope module tb $end
$var reg 2 ! data[1:0] $end
$var reg 1 " enable $end
$var reg 1 # address $end
$var reg 1 $ out_value $end
$scope module uut $end
$var reg 2 % data[1:0] $end
$var reg 1 & enable $end
$var reg 1 ' address $end
$var reg 1 ( out_value $end
$upscope $end
$upscope $end
$enddefinitions $end
#0
b00 !
0"
0#
X$
b00 %
0&
0'
X(
#1000000
b01 !
b01 %
#2000000
b10 !
b10 %
#3000000
b11 !
b11 %
#4000000
b00 !
1#
b00 %
1'
#5000000
b01 !
0#
b01 %
0'
#6000000
b10 !
b10 %
#7000000
b11 !
b11 %
#8000000
b00 !
1"
0$
b00 %
1&
0(
#9000000
b01 !
1$
b01 %
1(
#10000000
b10 !
0$
b10 %
0(
#11000000
b11 !
1$
b11 %
1(
#12000000
b00 !
1#
0$
b00 %
1'
0(
#13000000
b01 !
b01 %
#14000000
b10 !
1$
b10 %
1(
#15000000
b11 !
b11 %
