Functional AND_OR_AND/sklop_funkcijski.vhdl
library IEEE;
use IEEE.std_logic_1164.all;

ENTITY sklop_funkcijski IS PORT(
	a,b,c,d:IN std_logic;
	y:OUT std_logic);
END sklop_funkcijski;

ARCHITECTURE arch OF sklop_funkcijski IS
BEGIN
	process(a,b,c,d)
		variable temp:std_logic;

	BEGIN
		temp:='0';
		if d = '1' then
			if a = '1' and b = '1' then
				temp:='1';
			elsif c = '1' then
				temp:='1';
			end if;
		end if;

		y<=temp;
	END PROCESS;
END arch;

Functional AND_OR_AND/tb.vhdl
library IEEE;
use IEEE.std_logic_1164.all;

ENTITY tb IS
END tb;

ARCHITECTURE arch OF tb IS
	COMPONENT sklop_funkcijski
	PORT(
		a,b,c,d:IN std_logic;
		y:OUT std_logic );
	END COMPONENT;

	SIGNAL a,b,c,d,y : std_logic;
BEGIN
	sklop:sklop_funkcijski port map(a => a, b => b, c => c, d => d, y => y);

	PROCESS BEGIN
		a <= 'X';
		b <= 'X';
		c <= 'X';
		d <= 'X';
		wait for 1 ns;

		a <= '0';
		b <= '0';
		c <= '0';
		d <= '0';
		wait for 1 ns;
		
		a <= '0';
		b <= '0';
		c <= '0';
		d <= '1';
		wait for 1 ns;
		
		a <= '0';
		b <= '0';
		c <= '1';
		d <= '0';
		wait for 1 ns;
		
		a <= '0';
		b <= '0';
		c <= '1';
		d <= '1';
		wait for 1 ns;

		a <= '0';
		b <= '1';
		c <= '0';
		d <= '0';
		wait for 1 ns;

		a <= '0';
		b <= '1';
		c <= '0';
		d <= '1';
		wait for 1 ns;

		a <= '0';
		b <= '1';
		c <= '1';
		d <= '0';
		wait for 1 ns;

		a <= '0';
		b <= '1';
		c <= '1';
		d <= '1';
		wait for 1 ns;
		
		a <= '1';
		b <= '0';
		c <= '0';
		d <= '0';
		wait for 1 ns;
		
		a <= '1';
		b <= '0';
		c <= '0';
		d <= '1';
		wait for 1 ns;
		
		a <= '1';
		b <= '0';
		c <= '1';
		d <= '0';
		wait for 1 ns;

		a <= '1';
		b <= '0';
		c <= '1';
		d <= '1';
		wait for 1 ns;
		
		a <= '1';
		b <= '1';
		c <= '0';
		d <= '0';
		wait for 1 ns;
		
		a <= '1';
		b <= '1';
		c <= '0';
		d <= '1';
		wait for 1 ns;
		
		a <= '1';
		b <= '1';
		c <= '1';
		d <= '0';
		wait for 1 ns;
		
		a <= '1';
		b <= '1';
		c <= '1';
		d <= '1';
		wait for 1 ns;

		assert false report "End of test";
		WAIT;
	END PROCESS;
END arch;

Functional AND_OR_AND/waveform.vcd
$date
  Tue Apr 09 15:39:25 2019
$end
$version
  GHDL v0
$end
$timescale
  1 fs
$end
$scope module standard $end
$upscope $end
$scope module std_logic_1164 $end
$upscope $end
$scope module tb $end
$var reg 1 ! a $end
$var reg 1 " b $end
$var reg 1 # c $end
$var reg 1 $ d $end
$var reg 1 % y $end
$scope module sklop $end
$var reg 1 & a $end
$var reg 1 ' b $end
$var reg 1 ( c $end
$var reg 1 ) d $end
$var reg 1 * y $end
$upscope $end
$upscope $end
$enddefinitions $end
#0
X!
X"
X#
X$
0%
X&
X'
X(
X)
0*
#1000000
0!
0"
0#
0$
0&
0'
0(
0)
#2000000
1$
1)
#3000000
1#
0$
1(
0)
#4000000
1$
1%
1)
1*
#5000000
1"
0#
0$
0%
1'
0(
0)
0*
#6000000
1$
1)
#7000000
1#
0$
1(
0)
#8000000
1$
1%
1)
1*
#9000000
1!
0"
0#
0$
0%
1&
0'
0(
0)
0*
#10000000
1$
1)
#11000000
1#
0$
1(
0)
#12000000
1$
1%
1)
1*
#13000000
1"
0#
0$
0%
1'
0(
0)
0*
#14000000
1$
1%
1)
1*
#15000000
1#
0$
0%
1(
0)
0*
#16000000
1$
1%
1)
1*
