MUX21_with_basic_components/or_sklop.vhdl
library IEEE;
use IEEE.std_logic_1164.all;

ENTITY or_sklop IS PORT
(
	a,b: IN std_logic;
	y : OUT std_logic);
END or_sklop;

ARCHITECTURE arch OF or_sklop IS
BEGIN
	y <= a OR b;
END arch;

MUX21_with_basic_components/and_sklop.vhdl
library IEEE;
use IEEE.std_logic_1164.all;

ENTITY and_sklop IS PORT
(
	a,b,e : IN std_logic;
	o : OUT std_logic);
END and_sklop;

ARCHITECTURE arch OF and_sklop IS
BEGIN
	PROCESS(a,b,e)
	BEGIN
		if e = '0' then
			o <= '0';
		else
			o <= a AND b;
		end if;
	END PROCESS;
END arch;

MUX21_with_basic_components/invertor.vhdl
library IEEE;
use IEEE.std_logic_1164.all;

ENTITY invertor IS PORT
(
	i : IN std_logic;
	o : OUT std_logic);
END invertor;

ARCHITECTURE arch OF invertor IS
BEGIN
	o <= NOT(i);
END arch;

MUX21_with_basic_components/mux_21_osnovni_sklopovi.vhdl
library IEEE;
use IEEE.std_logic_1164.all;

ENTITY mux_21_osnovni_sklopovi IS PORT
(
	d: IN std_logic_vector(1 DOWNTO 0);
	a,e : IN std_logic;
	y : OUT std_logic);
END mux_21_osnovni_sklopovi;

ARCHITECTURE arch OF mux_21_osnovni_sklopovi IS
	SIGNAL m1, m2, inv : std_logic;
BEGIN
	s1: ENTITY work.invertor PORT MAP(i => a, o => inv);
	s2:	ENTITY work.and_sklop PORT MAP(a => inv, b => d(0), e => e, o => m1);
	s3:	ENTITY work.and_sklop PORT MAP(a => a,b => d(1), e => e, o => m2);
	s4:	ENTITY work.or_sklop PORT MAP(a => m1, b => m2, y => y);
END arch;

MUX21_with_basic_components/tb.vhdl
library IEEE;
use IEEE.std_logic_1164.all;

ENTITY tb IS
END tb;

ARCHITECTURE arch OF tb IS
	COMPONENT mux_21_osnovni_sklopovi
	PORT
	(
		d: IN std_logic_vector(1 DOWNTO 0);
		a,e : IN std_logic;
		y : OUT std_logic);
	END COMPONENT;

	SIGNAL d : std_logic_vector(1 DOWNTO 0);
	SIGNAL a,e,y : std_logic;

BEGIN
	mux : mux_21_osnovni_sklopovi port map(d => d, a => a, e => e, y => y);

	PROCESS
	BEGIN
		e <= 'X';
		d <= "XX";
		a <= 'X';
		wait for 1 ns;

		e <= '0';
		d <= "00";
		a <= '0';
		wait for 1 ns;

		e <= '0';
		d <= "00";
		a <= '1';
		wait for 1 ns;

		e <= '0';
		d <= "00";
		a <= '1';
		wait for 1 ns;

		e <= '0';
		d <= "01";
		a <= '0';
		wait for 1 ns;

		e <= '0';
		d <= "01";
		a <= '1';
		wait for 1 ns;
	
		e <= '0';
		d <= "10";
		a <= '0';
		wait for 1 ns;

		e <= '0';
		d <= "10";
		a <= '1';
		wait for 1 ns;

		e <= '1';
		d <= "00";
		a <= '0';
		wait for 1 ns;

		e <= '1';
		d <= "00";
		a <= '1';
		wait for 1 ns;

		e <= '1';
		d <= "01";
		a <= '0';
		wait for 1 ns;

		e <= '1';
		d <= "01";
		a <= '1';
		wait for 1 ns;

		e <= '1';
		d <= "10";
		a <= '0';
		wait for 1 ns;

		e <= '1';
		d <= "10";
		a <= '1';
		wait for 1 ns;

		e <= '1';
		d <= "11";
		a <= '1';
		wait for 1 ns;
		
		e <= '1';
		d <= "11";
		a <= '0';
		wait for 1 ns;

		assert false report "End of test";
		WAIT;
	END PROCESS;
END arch;

MUX21_with_basic_components/waveform.vcd
$date
  Tue Apr 16 12:50:16 2019
$end
$version
  GHDL v0
$end
$timescale
  1 fs
$end
$scope module standard $end
$upscope $end
$scope module std_logic_1164 $end
$upscope $end
$scope module tb $end
$var reg 2 ! d[1:0] $end
$var reg 1 " a $end
$var reg 1 # e $end
$var reg 1 $ y $end
$scope module mux $end
$var reg 2 % d[1:0] $end
$var reg 1 & a $end
$var reg 1 ' e $end
$var reg 1 ( y $end
$var reg 1 ) m1 $end
$var reg 1 * m2 $end
$var reg 1 + inv $end
$scope module s1 $end
$var reg 1 , i $end
$var reg 1 - o $end
$upscope $end
$scope module s2 $end
$var reg 1 . a $end
$var reg 1 / b $end
$var reg 1 0 e $end
$var reg 1 1 o $end
$upscope $end
$scope module s3 $end
$var reg 1 2 a $end
$var reg 1 3 b $end
$var reg 1 4 e $end
$var reg 1 5 o $end
$upscope $end
$scope module s4 $end
$var reg 1 6 a $end
$var reg 1 7 b $end
$var reg 1 8 y $end
$upscope $end
$upscope $end
$upscope $end
$enddefinitions $end
#0
bXX !
X"
X#
X$
bXX %
X&
X'
X(
X)
X*
X+
X,
X-
X.
X/
X0
X1
X2
X3
X4
X5
X6
X7
X8
#1000000
b00 !
0"
0#
0$
b00 %
0&
0'
0(
0)
0*
1+
0,
1-
1.
0/
00
01
02
03
04
05
06
07
08
#2000000
1"
1&
0+
1,
0-
0.
12
#3000000
#4000000
b01 !
0"
b01 %
0&
1+
0,
1-
1.
1/
02
#5000000
1"
1&
0+
1,
0-
0.
12
#6000000
b10 !
0"
b10 %
0&
1+
0,
1-
1.
0/
02
13
#7000000
1"
1&
0+
1,
0-
0.
12
#8000000
b00 !
0"
1#
b00 %
0&
1'
1+
0,
1-
1.
10
02
03
14
#9000000
1"
1&
0+
1,
0-
0.
12
#10000000
b01 !
0"
1$
b01 %
0&
1(
1)
1+
0,
1-
1.
1/
11
02
16
18
#11000000
1"
0$
1&
0(
0)
0+
1,
0-
0.
01
12
06
08
#12000000
b10 !
0"
b10 %
0&
1+
0,
1-
1.
0/
02
13
#13000000
1"
1$
1&
1(
1*
0+
1,
0-
0.
12
15
17
18
#14000000
b11 !
b11 %
1/
#15000000
0"
1$
0&
1(
1)
0*
1+
0,
1-
1.
11
02
05
16
07
18
